llmpromptkit/__init__.py
llmpromptkit/cli/__init__.py
llmpromptkit/cli/commands.py
llmpromptkit/core/__init__.py
llmpromptkit/core/evaluation.py
llmpromptkit/core/prompt_manager.py
llmpromptkit/core/testing.py
llmpromptkit/core/version_control.py
llmpromptkit/utils/__init__.py
llmpromptkit/utils/metrics.py
llmpromptkit/utils/storage.py
llmpromptkit/utils/templating.py
llmpromptkit-0.1.0.dist-info/licenses/LICENSE
llmpromptkit-0.1.0.dist-info/METADATA
llmpromptkit-0.1.0.dist-info/WHEEL
llmpromptkit-0.1.0.dist-info/entry_points.txt
llmpromptkit-0.1.0.dist-info/top_level.txt
llmpromptkit-0.1.0.dist-info/RECORD
