Metadata-Version: 2.4
Name: llmpromptkit
Version: 0.1.0
Summary: A comprehensive LLM Prompt Management System
Author: Biswanath Roul
Maintainer: Biswanath Roul
License: MIT
Project-URL: Homepage, https://github.com/biswanathroul/llmpromptkit
Project-URL: Bug Tracker, https://github.com/biswanathroul/llmpromptkit/issues
Project-URL: Documentation, https://github.com/biswanathroul/llmpromptkit/wiki
Project-URL: Source Code, https://github.com/biswanathroul/llmpromptkit
Keywords: llm,prompt engineering,nlp,machine learning
Classifier: Development Status :: 3 - Alpha
Classifier: Intended Audience :: Developers
Classifier: Intended Audience :: Science/Research
Classifier: License :: OSI Approved :: MIT License
Classifier: Programming Language :: Python :: 3
Classifier: Programming Language :: Python :: 3.7
Classifier: Programming Language :: Python :: 3.8
Classifier: Programming Language :: Python :: 3.9
Classifier: Programming Language :: Python :: 3.10
Classifier: Topic :: Scientific/Engineering :: Artificial Intelligence
Requires-Python: >=3.7
License-File: LICENSE
Requires-Dist: numpy>=1.20.0
Dynamic: license-file
